{
  "id": 546,
  "kanji": "市",
  "readings": [
    "シ",
    "いち"
  ],
  "wordsRequiredNow": [
    {
      "kanji": "＿市",
      "reading": "シ",
      "meaning": "… miasto (sufiks)"
    },
    {
      "kanji": "都市",
      "reading": "トシ",
      "meaning": "miasto; metropolia"
    },
    {
      "kanji": "市民",
      "reading": "シミン",
      "meaning": "obywatel; mieszkaniec miasta"
    },
    {
      "kanji": "市役所",
      "reading": "シヤクショ",
      "meaning": "ratusz; urząd miejski"
    },
    {
      "kanji": "市場",
      "reading": "いちば",
      "meaning": "targ; bazar"
    },
    {
      "kanji": "市場",
      "reading": "シジョウ",
      "meaning": "rynek (ekonomiczny)"
    }
  ],
  "wordsRequiredLater": [
    {
      "kanji": "市街",
      "reading": "シガイ",
      "reference": 1202
    },
    {
      "kanji": "旧市街",
      "reading": "キュウシガイ",
      "reference": 1203
    },
    {
      "kanji": "新潟市",
      "reading": "にいがたシ",
      "meaning": "miasto Niigata",
      "reference": 1352
    }
  ],
  "additionalWords": []
}
